zensols/pybuild/__init__.py
zensols/pybuild/cli.py
zensols/pybuild/remote.py
zensols/pybuild/setuputil.py
zensols/pybuild/tag.py
zensols/pybuild/version.py
zensols.pybuild-0.1.1.dist-info/METADATA
zensols.pybuild-0.1.1.dist-info/WHEEL
zensols.pybuild-0.1.1.dist-info/entry_points.txt
zensols.pybuild-0.1.1.dist-info/top_level.txt
zensols.pybuild-0.1.1.dist-info/RECORD
