Metadata-Version: 2.1
Name: zensols.pybuild
Version: 0.1.1
Summary: Inspect and iterate on git tags.  This manages tags in a git repository.
Home-page: https://github.com/plandes/zenpybuild
Download-URL: https://github.com/plandes/zenpybuild/releases/download/v0.1.1/zensols.pybuild-0.1.1-py3-none-any.whl
Author: Paul Landes
Author-email: landes@mailc.net
Keywords: tooling
Requires-Dist: GitPython ~=3.1.29
Requires-Dist: gitdb2 ~=2.0.3
Requires-Dist: plac
